README.rst
setup.cfg
setup.py
roboarm/__init__.py
roboarm/const.py
roboarm/exceptions.py
roboarm/parts.py
roboarm/roboarm.py
roboarm.egg-info/PKG-INFO
roboarm.egg-info/SOURCES.txt
roboarm.egg-info/dependency_links.txt
roboarm.egg-info/entry_points.txt
roboarm.egg-info/requires.txt
roboarm.egg-info/top_level.txt
roboarm.egg-info/zip-safe