Metadata-Version: 1.1
Name: roboarm
Version: 1.0dev
Summary: Python library for controlling owi robotic arm edge
Home-page: https://github.com/nvbn/roboarm
Author: Vladimir Iakovlev
Author-email: nvbn.rm@gmail.com
License: BSD
Platform: UNKNOWN
Classifier: Programming Language :: Python
Classifier: Programming Language :: Python :: 3
